waveplate/__init__.py
waveplate/simulation.py
waveplate-0.0.5.dist-info/LICENSE
waveplate-0.0.5.dist-info/METADATA
waveplate-0.0.5.dist-info/WHEEL
waveplate-0.0.5.dist-info/top_level.txt
waveplate-0.0.5.dist-info/RECORD
