Metadata-Version: 2.1
Name: waveplate
Version: 0.0.5
Summary: A python library for simulating optics
Home-page: UNKNOWN
Author: Quantum Visionary Labs
Author-email: <qvllabs@gmail.com>
License: UNKNOWN
Keywords: python,optics,photonics,photons,physics,quantum mechanics
Platform: UNKNOWN
Classifier: Development Status :: 1 - Planning
Classifier: Intended Audience :: Developers
Classifier: Programming Language :: Python :: 3
Classifier: Operating System :: Unix
Classifier: Operating System :: MacOS :: MacOS X
Classifier: Operating System :: Microsoft :: Windows
License-File: LICENSE
Requires-Dist: numpy
